flightaware_history/__init__.py
flightaware_history/__main__.py
flightaware_history/kml.py
flightaware_history/scraper.py
flightaware_history_rolandcrosby-0.1.0.dist-info/METADATA
flightaware_history_rolandcrosby-0.1.0.dist-info/WHEEL
flightaware_history_rolandcrosby-0.1.0.dist-info/entry_points.txt
flightaware_history_rolandcrosby-0.1.0.dist-info/top_level.txt
flightaware_history_rolandcrosby-0.1.0.dist-info/RECORD
