Metadata-Version: 2.1
Name: flightaware-history-rolandcrosby
Version: 0.1.0
Summary: Retrieve flight track logs from FlightAware as KML files
Home-page: https://github.com/rolandcrosby/flightaware-history
Author: Roland Crosby
Author-email: roland@rolandcrosby.com
License: 0BSD
Platform: UNKNOWN
Requires-Python: >=3.8
Requires-Dist: lxml (>=4.5)
Requires-Dist: MechanicalSoup (>=0.12)
